Metadata-Version: 2.1
Name: seoman
Version: 0.1.11
Summary: A Command Line tool that is designed for technical SEOs
Home-page: https://seo.do/
License: Apache 2.0
Keywords: seo,technical seo
Author: seo.do
Author-email: yagizcan@zeo.org
Maintainer: Yagiz Degirmenci
Maintainer-email: yagizcan@zeo.org
Requires-Python: >=3.6,<4.0
Classifier: License :: Other/Proprietary License
Classifier: Programming Language :: Python :: 3
Classifier: Programming Language :: Python :: 3.10
Classifier: Programming Language :: Python :: 3.6
Classifier: Programming Language :: Python :: 3.7
Classifier: Programming Language :: Python :: 3.8
Classifier: Programming Language :: Python :: 3.9
Requires-Dist: dateparser (>=1.1.0,<2.0.0)
Requires-Dist: google-api-python-client (>=1.12.5,<2.0.0)
Requires-Dist: google-auth-oauthlib (>=0.4.1,<0.5.0)
Requires-Dist: halo (>=0.0.30,<0.0.31)
Requires-Dist: inquirer (>=2.7.0,<3.0.0)
Requires-Dist: pyexcelerate (>=0.9.0,<0.10.0)
Requires-Dist: pytablewriter (>=0.58.0,<0.59.0)
Requires-Dist: requests (>=2.24.0,<3.0.0)
Requires-Dist: toml (>=0.10.1,<0.11.0)
Requires-Dist: typer (>=0.3.2,<0.4.0)
Project-URL: Repository, https://github.com/zeoagency/seoman
